{
    "processors": [
        {
            "type": "add_world",
            "world": "event/grid_runners"
        },
        {
            "comment": "Custom assembler to create the Grid Runners arena and paste in all selected rooms.",
            "type": "grid_runners_assembler",
            "selectedPreset": "mcc18",
            "presets": {
                "mcc16": [
                    "jungle_temple",
                    "bakery",
                    "saw_mill",
                    "wild_west",
                    "kitchen",
                    "golf",
                    "factory_tower",
                    "prison",
                    "conveyors"
                ],
                "mcc17": [
                    "city_targets",
                    "city_statue",
                    "bakery",
                    "art_gallery",
                    "city_lamps",
                    "kitchen",
                    "city_canal_key",
                    "sewer_crossing",
                    "weave"
                ],
                "mccrising": [
                    "city_statue",
                    "jungle_temple",
                    "art_gallery",
                    "wild_west",
                    "city_lamps",
                    "golf",
                    "city_canal_key",
                    "prison",
                    "weave"
                ],
                "mcc18": [
                    "bakery_halloween",
                    "jungle_temple_halloween",
                    "saw_mill",
                    "shoot_eyes",
                    "stone_pyramid_key",
                    "brew_potions",
                    "pumpkin_carve",
                    "colour_bridge_lamps",
                    "conveyors"
                ]
            }
        },
        {
            "type": "remove_sections",
            "sections": ["ref_rooms"]
        },
        {
            "type": "lighting_updater"
        },
        {
            "type": "empty_region_padding"
        }
    ]
}
