{
    "input": {
        "type": "build_server",
        "name": "build_mart"
    },
    "sections": {
        "classic": [
            [0, 0]
        ],
        "sky": [
            [2, 0]
        ],
        "ref_builds": [
            [-18, 11],
            [-17, 11]
        ]
    },
    "processors": [
        {
            "type": "scanner",
            "filter": {
                "type": "DENY",
                "entries": [
                    "ref_builds"
                ]
            },
            "targets": {
                "spawnpoints": {
                    "type": "grouped",
                    "block": "mcc:markers/player_spawnpoints"
                },
                "spectator_spawnpoint": {
                    "type": "single",
                    "block": "mcc:markers/spectator_spawnpoint"
                }
            }
        },
        {
            "type": "scanner",
            "filter": {
                "strategy": "ALLOW",
                "entries": [
                    "ref_builds"
                ]
            },
            "targets": {
                "build_corners": {
                    "type": "single",
                    "block": "mcc:markers/build_mart/build_template"
                }
            }
        },
        {
            "type": "lighting_updater"
        },
        {
            "type": "split_world_per_section",
            "filter": {
                "type": "DENY",
                "entries": [
                    "ref_builds"
                ]
            }
        },
        {
            "type": "empty_region_padding"
        }
    ]
}